futurx-brain-mcp/__main__.py
futurx_brain_mcp/__init__.py
futurx_brain_mcp/__main__.py
futurx_brain_mcp/server.py
futurx_brain_mcp-0.1.8.dist-info/METADATA
futurx_brain_mcp-0.1.8.dist-info/WHEEL
futurx_brain_mcp-0.1.8.dist-info/entry_points.txt
futurx_brain_mcp-0.1.8.dist-info/top_level.txt
futurx_brain_mcp-0.1.8.dist-info/RECORD
