Metadata-Version: 2.4
Name: futurx-brain-mcp
Version: 0.1.8
Summary: futurx brain mcp server
Requires-Python: >=3.10
Requires-Dist: mcp[cli]>=1.6.0
Requires-Dist: requests>=2.32.3
